zeekutils/__init__.py
zeekutils/utils.py
zeekutils/zeek.py
zeekutils/zeekNodes.py
zeekutils/zeekRule.py
zeekutils-0.1.dist-info/METADATA
zeekutils-0.1.dist-info/WHEEL
zeekutils-0.1.dist-info/top_level.txt
zeekutils-0.1.dist-info/RECORD
