Metadata-Version: 2.1
Name: zeekutils
Version: 0.1
Summary: zeek utils
Home-page: https://aspirepig.cn
Author: aspirepig
Author-email: aspirepig@gmail.com
License: Public domain
Platform: any
